prettyalgo/__init__.py
prettyalgo/pprint.py
prettyalgo/tests/__init__.py
prettyalgo/tests/test_pprint.py
prettyalgo-0.0.3.dist-info/METADATA
prettyalgo-0.0.3.dist-info/WHEEL
prettyalgo-0.0.3.dist-info/licenses/LICENSE
prettyalgo-0.0.3.dist-info/RECORD
