Metadata-Version: 2.4
Name: prettyalgo
Version: 0.0.3
Summary: prettyalgo - pretty print for programming puzzles.
Project-URL: Homepage, https://github.com/adamhadani/prettyalgo
Project-URL: Issues, https://github.com/adamhadani/prettyalgo/issues
Author-email: Adam Ever-Hadani <adamhadani@gmail.com>
License-File: LICENSE
Classifier: License :: OSI Approved :: MIT License
Classifier: Operating System :: OS Independent
Classifier: Programming Language :: Python :: 3
Requires-Python: >=3.8
Requires-Dist: termcolor>=2.5.0
Provides-Extra: test
Requires-Dist: coverage; extra == 'test'
Requires-Dist: pytest; extra == 'test'
Requires-Dist: pytest-coverage; extra == 'test'
